autocamlight/__init__.py
autocamlight/__main__.py
autocamlight-0.2.0.dist-info/licenses/LICENSE
autocamlight-0.2.0.dist-info/WHEEL
autocamlight-0.2.0.dist-info/entry_points.txt
autocamlight-0.2.0.dist-info/METADATA
autocamlight-0.2.0.dist-info/RECORD
