Metadata-Version: 2.4
Name: autocamlight
Version: 0.2.0
Summary: Automate your webcam light.
Keywords: webcam,automation,home-assistant,mqtt,linux
Author: Dries007
Author-email: Dries007 <admin@dries007.net>
License-Expression: MIT
License-File: LICENSE
Classifier: Development Status :: 4 - Beta
Classifier: Environment :: Console
Classifier: Intended Audience :: End Users/Desktop
Classifier: License :: OSI Approved :: MIT License
Classifier: Operating System :: POSIX :: Linux
Classifier: Programming Language :: Python :: 3
Classifier: Programming Language :: Python :: 3.11
Classifier: Programming Language :: Python :: 3.12
Classifier: Programming Language :: Python :: 3.13
Classifier: Programming Language :: Python :: 3.14
Classifier: Topic :: System :: Hardware
Classifier: Topic :: Utilities
Requires-Dist: ha-mqtt-discoverable>=0.22.1
Requires-Dist: inotify>=0.2.12
Requires-Dist: pydantic-settings>=2.11.0
Requires-Python: >=3.11
Project-URL: Homepage, https://github.com/Dries007/AutoCamLight
Project-URL: Issues, https://github.com/Dries007/AutoCamLight/issues
Project-URL: Paypal, https://www.paypal.me/Dries007
Project-URL: Repository, https://github.com/Dries007/AutoCamLight.git
